cache_expire.py
cache_expire-1.0.0.dist-info/DESCRIPTION.rst
cache_expire-1.0.0.dist-info/METADATA
cache_expire-1.0.0.dist-info/RECORD
cache_expire-1.0.0.dist-info/WHEEL
cache_expire-1.0.0.dist-info/metadata.json
cache_expire-1.0.0.dist-info/top_level.txt
