Metadata-Version: 2.0
Name: cache-expire
Version: 1.0.0
Summary: Memoize decorator with expire timeout.
Home-page: https://github.com/kjwon15/cache-expire
Author: Kjwon15
Author-email: UNKNOWN
License: UNKNOWN
Platform: UNKNOWN
